tom_antares/__init__.py
tom_antares/antares.py
tom_antares/tests/__init__.py
tom_antares/tests/boot_django.py
tom_antares/tests/django_shell.py
tom_antares/tests/factories.py
tom_antares/tests/run_canary_tests.py
tom_antares/tests/run_tests.py
tom_antares/tests/tests.py
tom_antares/tests/tests_canary.py
tom_antares-1.2.6.dist-info/LICENSE
tom_antares-1.2.6.dist-info/METADATA
tom_antares-1.2.6.dist-info/WHEEL
tom_antares-1.2.6.dist-info/top_level.txt
tom_antares-1.2.6.dist-info/RECORD
