Metadata-Version: 2.1
Name: tom-antares
Version: 1.2.6
Summary: Antares broker module for the TOM Toolkit
Home-page: https://tomtoolkit.github.io
Author: TOM Toolkit Project
Author-email: llindstrom@lco.global, dmcollom@gmail.com
Keywords: tomtoolkit,astronomy,astrophysics,cosmology,science,fits,observatory,antares
Classifier: Development Status :: 3 - Alpha
Classifier: Intended Audience :: Science/Research
Classifier: License :: OSI Approved :: BSD License
Classifier: Operating System :: OS Independent
Classifier: Programming Language :: Python :: 3
Classifier: Programming Language :: Python :: 3.8
Classifier: Topic :: Scientific/Engineering :: Astronomy
Classifier: Topic :: Scientific/Engineering :: Physics
License-File: LICENSE
Requires-Dist: tomtoolkit <3.0,>=2.12
Requires-Dist: antares-client <2.0,>=1.4
Requires-Dist: elasticsearch-dsl <7.5,>=7.3
Provides-Extra: test
Requires-Dist: factory-boy <3.4,>=3.1 ; extra == 'test'
